goodvibes/GoodVibes.py
goodvibes/__init__.py
goodvibes/__main__.py
goodvibes/media.py
goodvibes/test.py
goodvibes/vib_scale_factors.py
goodvibes/examples/Al_298K.out
goodvibes/examples/Al_400K.out
goodvibes/examples/CuCN.out
goodvibes/examples/H2O.out
goodvibes/examples/HCN_singlet.out
goodvibes/examples/HCN_triplet.out
goodvibes/examples/allene.out
goodvibes/examples/benzene.out
goodvibes/examples/ethane.out
goodvibes/examples/ethane_TZ.out
goodvibes/examples/ethane_spc.out
goodvibes/examples/isobutane.out
goodvibes/examples/methane.log
goodvibes/examples/methylaniline.out
goodvibes/examples/neopentane.out
goodvibes/examples/gconf_ee_boltz/Aminoxylation_TS1_R.log
goodvibes/examples/gconf_ee_boltz/Aminoxylation_TS2_S.log
goodvibes/examples/gconf_ee_boltz/aminox_cat_conf212_S.log
goodvibes/examples/gconf_ee_boltz/aminox_cat_conf280_R.log
goodvibes/examples/gconf_ee_boltz/aminox_cat_conf65_S.log
goodvibes/examples/gconf_ee_boltz/aminox_subs_conf713.log
goodvibes/examples/gconf_ee_boltz/gconf_TS.yaml
goodvibes/examples/gconf_ee_boltz/gconf_aminox_cat.yaml
goodvibes/examples/media_conc/Benzene.log
goodvibes/examples/media_conc/H2O.log
goodvibes/examples/media_conc/MeOH.log
goodvibes/examples/pes/Cis_complete_pathway.yaml
goodvibes/examples/pes/Int-III_Oax_cis_a.log
goodvibes/examples/pes/Int-II_Oax_cis_a.log
goodvibes/examples/pes/Int-I_Oax.log
goodvibes/examples/pes/TolS.log
goodvibes/examples/pes/TolSH.log
goodvibes/share/symmetry.c
goodvibes/share/symmetry_linux.so
goodvibes/share/symmetry_mac.dylib
goodvibes/share/symmetry_windows.dll
goodvibes-3.0.1.dist-info/LICENSE.txt
goodvibes-3.0.1.dist-info/METADATA
goodvibes-3.0.1.dist-info/WHEEL
goodvibes-3.0.1.dist-info/top_level.txt
goodvibes-3.0.1.dist-info/RECORD
