Metadata-Version: 2.1
Name: goodvibes
Version: 3.0.1
Summary: A python program to compute corrections to thermochemical data from frequency calculations
Home-page: https://github.com/bobbypaton/goodvibes
Author: Paton Research Group
Author-email: robert.paton@colostate.edu
License: UNKNOWN
Download-URL: https://github.com/bobbypaton/GoodVibes/archive/v3.0.1.zip
Keywords: compchem,thermochemistry,gaussian,vibrational-entropies,temperature
Platform: UNKNOWN
Requires-Python: >=2.6
Requires-Dist: numpy
